nornir_ops.py
server.py
iflow_mcp_yhvh_chen_nornir_mcp-0.2.0.dist-info/METADATA
iflow_mcp_yhvh_chen_nornir_mcp-0.2.0.dist-info/WHEEL
iflow_mcp_yhvh_chen_nornir_mcp-0.2.0.dist-info/entry_points.txt
iflow_mcp_yhvh_chen_nornir_mcp-0.2.0.dist-info/licenses/LICENSE
iflow_mcp_yhvh_chen_nornir_mcp-0.2.0.dist-info/RECORD
