Metadata-Version: 2.4
Name: iflow-mcp_yhvh-chen-nornir-mcp
Version: 0.2.0
Summary: Nornir MCP server for network automation
Author: yhvh.chen
License: MIT
License-File: LICENSE
Requires-Python: >=3.10
Requires-Dist: mcp[cli]==1.15.0
Requires-Dist: nornir-napalm
Requires-Dist: nornir==3.5.0
Requires-Dist: sse-starlette
Provides-Extra: dev
Requires-Dist: black; extra == 'dev'
Requires-Dist: isort; extra == 'dev'
Requires-Dist: pytest; extra == 'dev'
